lnmetrics_api/__init__.py
lnmetrics_api/lnmetrics_client.py
lnmetrics_api/queries/__init__.py
lnmetrics_api/queries/queries.py
lnmetrics_api-0.0.7.dist-info/LICENSE
lnmetrics_api-0.0.7.dist-info/METADATA
lnmetrics_api-0.0.7.dist-info/WHEEL
lnmetrics_api-0.0.7.dist-info/RECORD
