Metadata-Version: 2.1
Name: lnmetrics-api
Version: 0.0.7
Summary: Python implementation of the lnmetrics API to query the lnmetrics services
Author: Vincenzo Palazzo
Author-email: vincenzopalazzodev@gmail.com
Requires-Python: >=3.7,<4.0
Classifier: Programming Language :: Python :: 3
Classifier: Programming Language :: Python :: 3.7
Classifier: Programming Language :: Python :: 3.8
Classifier: Programming Language :: Python :: 3.9
Classifier: Programming Language :: Python :: 3.10
Classifier: Programming Language :: Python :: 3.11
Requires-Dist: aiohttp (>=3.8.1,<4.0.0)
Requires-Dist: gql (>=3.1.0,<4.0.0)
Requires-Dist: requests (>=2.27.1,<3.0.0)
Requires-Dist: requests-toolbelt (>=0.9.1,<0.10.0)
